puncia/__init__.py
puncia/__main__.py
puncia/puncia.py
puncia/test.py
puncia-0.34.dist-info/LICENSE
puncia-0.34.dist-info/METADATA
puncia-0.34.dist-info/WHEEL
puncia-0.34.dist-info/entry_points.txt
puncia-0.34.dist-info/top_level.txt
puncia-0.34.dist-info/RECORD
