Metadata-Version: 2.2
Name: puncia
Version: 0.34
Summary: Panthera(P.)uncia - Official CLI utility for Osprey Vision, Subdomain Center & Exploit Observer
Home-page: https://github.com/ARPSyndicate/puncia
Author: A.R.P. Syndicate
Author-email: ayush@arpsyndicate.io
License: MIT
Project-URL: A.R.P. Syndicate, https://www.arpsyndicate.io
Project-URL: Subdomain Center, https://subdomain.center
Project-URL: Exploit Observer, https://exploit.observer
Project-URL: Osprey Vision, https://osprey.vision
Keywords: information discovery cyber intelligence llm ai chat subdomains subdomain exploits exploit sbom cyclonedx arpsyndicate panthera uncia puncia snow leopard
License-File: LICENSE
Requires-Dist: requests
Requires-Dist: aiohttp
Requires-Dist: aiofiles
Requires-Dist: asyncio
Dynamic: author
Dynamic: author-email
Dynamic: description
Dynamic: description-content-type
Dynamic: home-page
Dynamic: keywords
Dynamic: license
Dynamic: project-url
Dynamic: requires-dist
Dynamic: summary
